{"version":0,"data":[{"instancePath":"grp_bgn_inference_Pipeline_LAYER1_VITIS_LOOP_44_1_fu_79","loopName":"LAYER1_VITIS_LOOP_44_1","loopLatencyAvg":"16016","loopLatencyMax":"16016","loopLatencyMin":"16016","loopIIAvg":"","loopIIMax":"","loopIIMin":"","iterLatencyAvg":"17","iterLatencyMax":"17","iterLatencyMin":"17","iterIIAvg":"1","iterIIMax":"1","iterIIMin":"1","startEndEachLoop":"","startEndEachIter":""},{"instancePath":"grp_bgn_inference_Pipeline_LAYER2_VITIS_LOOP_79_2_fu_93","loopName":"LAYER2_VITIS_LOOP_79_2","loopLatencyAvg":"6405","loopLatencyMax":"6405","loopLatencyMin":"6405","loopIIAvg":"","loopIIMax":"","loopIIMin":"","iterLatencyAvg":"6","iterLatencyMax":"6","iterLatencyMin":"6","iterIIAvg":"1","iterIIMax":"1","iterIIMin":"1","startEndEachLoop":"","startEndEachIter":""}]}
